DirectFolderBrowser/DetailView.py
DirectFolderBrowser/DirectFolderBrowser.py
DirectFolderBrowser/SymbolView.py
DirectFolderBrowser/__init__.py
DirectFolderBrowser/icons/File.png
DirectFolderBrowser/icons/Folder.png
DirectFolderBrowser/icons/FolderNew.png
DirectFolderBrowser/icons/FolderShowHidden.png
DirectFolderBrowser/icons/FolderUp.png
DirectFolderBrowser/icons/Reload.png
DirectFolderBrowser/icons/ViewTypeDetail.png
DirectFolderBrowser/icons/ViewTypeSymbol.png
DirectFolderBrowser-22.1.dist-info/LICENSE
DirectFolderBrowser-22.1.dist-info/METADATA
DirectFolderBrowser-22.1.dist-info/WHEEL
DirectFolderBrowser-22.1.dist-info/top_level.txt
DirectFolderBrowser-22.1.dist-info/RECORD
