Metadata-Version: 2.1
Name: DirectFolderBrowser
Version: 22.1
Summary: A simple file and folder browser for Panda3D
Home-page: https://github.com/fireclawthefox/DirectFolderBrowser
Author: Fireclaw
Author-email: fireclawthefox@gmail.com
License: UNKNOWN
Platform: UNKNOWN
Classifier: Programming Language :: Python :: 3
Classifier: License :: OSI Approved :: BSD License
Classifier: Operating System :: OS Independent
Classifier: Development Status :: 5 - Production/Stable
Classifier: Intended Audience :: Developers
Classifier: Intended Audience :: End Users/Desktop
Classifier: Topic :: Desktop Environment :: File Managers
Requires-Python: >=3.6
License-File: LICENSE
Requires-Dist: panda3d
